{
	"id": 3200,
	"name": "Adamant halberd",
	"description": "It's an Adamant halberd.",
	"value": "4774",
	"equipSlot": "weapon",
	"bonuses" : [
		28,
		41,
		0,
		-4,
		0,
		-1,
		3,
		4,
		0,
		0,
		42,
		0
	],
	"attackDelay": "7",
	"levelRequirements" : [
		0,
		0,
		0,
		0,
		0
	],
	"animations" : [
		809,
		0,
		1146,
		0,
		0,
		0,
		0
	],
	"combatAnimations" : [
		440,
		440,
		440,
		440,
		0
	],
	"twoHanded": false,
	"special": false,
	"stackable": false
}
